{"hans1":230,"winston1":240,"fifi1":230,"cookie1":800,"bernise1":600,"cameron1":250,"triston1":850,"lola2":700,"suneetha1":1000,"mykii1":600,"lola1":250,"beula1":2500,"bebe1":3000,"bernardo1":1400,"stacy1":850,"seth1":790,"poplina1":859,"patrona1":600,"maggie1":800,"scarlet1":1000,"toni1":1000,"tristan1":2000,"ashley1":2000,"kendla1":850,"shantira1":900,"charlie3":10000,"charlie1":1200,"poplina2":2500,"petula1":800,"wanda1":2000,"astin1":2500,"triston2":2500,"regina3":21000,"satine_easter1":20000,"satine_easter2":60000,"zozo1":1000,"danny3":19000,"safiyah1":2000,"tyree1":800,"maribel1":5000,"shun1":800,"caroleena_easter2":110000,"gigi1":3500,"omar1":800,"cameron3":2000,"chuey1":800,"sawyer1":2500,"astin2":6500,"henry1":2500,"chanel1":1600,"carmelita1":4500,"vas1":2000,"yollie1":1000,"leon1":2000,"cailey1":2000,"sid1":4000,"benny1":14600,"fifi2":700,"mo1":830,"seth3":7000,"yollie2":3200,"rudolph1":2500,"daxxon1":3000,"kendla3":8000,"rosie1":5500,"regina1":4000,"gordon1":3800,"chloe1":6500,"cameron2":800,"jonas1":5000,"carl1":1500,"avery1":7000,"clarice1":3000,"patty1":6500,"dabria1":850,"trinity1":2100,"omar2":2400,"vas2":3500,"wanda2":4900,"emma1":2600,"lola3":1800,"brock1":3500,"winston3":1500,"malcolm1":7500,"caroleena_easter1":45000,"lola4":4500,"henley1":2300,"gordon3":23250,"bebe3":18000,"maui3":21250,"sharie3":11000,"zuzana1":7000,"maribel2":13000,"keina1":5000,"cienna2":8000,"beula2":7500,"trinity2":5000,"omar3":9800,"mykii3":3600,"sabrina1":3500,"leonard1":5299,"rocky1":6000,"melani1":1500,"lesedi1":1200,"maui1":4500,"lindsay1":1500,"cici1":2000,"harrison1":2100,"maya1":2000,"michaela2":16000,"gracelynn1":1500,"xander1":800,"chloe2":15500,"dustin1":26750,"holly1":1700,"tracey1":2500,"odile2":5500,"patty_the_valentines_cow1":50000,"hans2":700,"kendla2":2500,"gary1":4500,"tatiana1":5000,"floyd_the_fries3":18000,"dawn1":2500,"odile1":2200,"danny1":4000,"patty3":27000,"winston2":700,"omar4":22000,"hans3":1500,"hermey1":3300,"emma2":6000,"cameron5":13000,"otto1":32500,"toni3":10000,"patrona2":1300,"scarlet2":3225,"wendy1":9500,"samir1":6400,"bernise2":1300,"bumble1":3000,"chanel3":13000,"tristan2":5000,"zozo2":3000,"henry3":14000,"bernardo2":3000,"leon2":5000,"mykii2":1300,"toni2":3000,"tyree2":2100,"leon5":60000,"ronnie1":8700,"kiki1":4800,"gracelynn2":4000,"seth2":2100,"fifi3":1700,"suneetha2":3125,"chuey2":2100,"gary2":11000,"archie1":6500,"trinity3":14000,"kondo2":25000,"sheldon3":25000,"cookie2":2300,"jonas2":14000,"kondo1":9000,"cienna1":2700,"satine_easter3":180000,"triston4":20000,"xiomara3":22000,"prince1":7500,"kiki3":23000,"chanel2":4200,"archie2":14000,"penny1":7100,"xiomara1":3999,"triston3":9000,"winston4":4000,"dallas_easter1":3000,"ronnie2":16000,"astin3":13000,"shun2":2400,"stacy2":2500,"maritza1":12000,"bernardo3":10250,"cookie3":6000,"dabria2":2400,"mo2":2500,"sheldon1":5500,"malcolm2":12750,"sunny2":12000,"charlie2":3500,"vas3":8500,"rocky3":26000,"astin5":60000,"fifi4":3900,"sharie1":3000,"gigi5":199500,"shantira2":2200,"zozo4":25000,"carmelita3":24500,"archie3":25000,"bernise3":4000,"sunny1":4500,"lola5":12000,"dallas_easter2":7500,"avery3":27000,"dante2":77500,"zozo3":10000,"benny4":85000,"gigi3":22000,"hans4":4000,"maggie2":2200,"floyd_the_fries1":3999,"shun3":6450,"holly2":4400,"maui2":10000,"molinda1":40000,"patrona4":7525,"zuzana2":18000,"patty2":15000,"vampirecameron1":60000,"lindsay2":4000,"brock2":8700,"stacy3":9450,"petula2":2300,"sid2":9700,"rudolph2":8100,"bebe2":7000,"carmelita4":75000,"chanel5":90000,"dante1":32000,"carmelita5":217500,"cannon1":19525,"dallas_easter3":23000,"tristan3":14000,"stacy4":21000,"ashley2":5300,"triston5":72000,"carl2":3700,"maggie3":10000,"safiyah2":5900,"benny2":25000,"leon3":11000,"gary3":24000,"chanel4":27000,"kevin1":9000,"gigi2":11000,"xiomara2":10000,"keina2":9000,"xander2":2000,"scarlet3":10000,"sabrina2":11000,"tyree3":6950,"ronnie3":28000,"lindsay3":15000,"michaela1":5000,"bernise5":35000,"zozo5":60000,"hans5":14000,"maritza3":45000,"bernise4":10000,"avery2":14000,"kevin3":35000,"dallas_easter4":62000,"lesedi2":4000,"patrona3":3500,"samir3":26000,"stix2":77000,"aimee_easter1":320000,"patty_the_valentines_cow2":120000,"lesedi3":15000,"yollie3":10000,"rosie2":10600,"stix1":30000,"dustin2":71500,"vas4":17500,"maya2":5000,"henry2":6000,"maribel3":40000,"tatiana3":20000,"kendla4":22000,"danny2":9650,"winston5":13000,"leonard2":12000,"penny2":18000,"maribel5":400000,"toni5":83500,"carmelita2":12000,"harrison2":5600,"brock3":18000,"cannon2":47900,"gordon2":8500,"wanda3":9700,"sunny3":27000,"yollie4":30000,"astin4":27000,"leonard3":22000,"jonas3":30000,"wendy2":18000,"prince2":20000,"leon4":25000,"gracelynn3":15250,"poplina3":8500,"bebe5":220000,"carl3":9000,"cici2":5000,"benny3":40000,"omar5":75000,"keina3":22500,"cameron4":4700,"gracelynn5":100000,"tracey2":7250,"wendy3":30000,"sabrina3":21000,"ronnie4":83500,"vas5":47000,"maritza2":26000,"fifi5":11400,"melani2":4500,"sawyer2":7500,"dawn3":19000,"odile5":150000,"penny3":26000,"mo3":6583,"kondo3":52000,"malcolm4":78500,"hermey2":9500,"sharie2":5250,"sunny5":220000,"daxxon2":8500,"floyd_the_fries2":7839,"shantira3":8950,"suneetha5":81000,"suneetha3":10000,"otto2":96000,"malcolm3":25250,"regina2":10000,"cailey2":6100,"charlie4":27000,"tatiana2":10000,"beula3":18000,"kiki2":9750,"archie4":74999,"rocky2":14000,"sheldon2":12000,"henley2":7500,"wanda5":82525,"tracey3":10950,"dawn2":7500,"ashley3":14000,"clarice2":9000,"scarlet5":89500,"bumble2":12000,"sid3":25000,"mykii4":9500,"maribel4":110000,"dabria3":7500,"chuey3":7200,"odile3":18000,"mo4":24500,"emma3":16000,"pep1":800,"glady1":800,"pep2":2400,"fresa1":800,"glady2":2200,"fresa2":2000,"pep3":7000,"glady3":8300,"pep4":19000,"fresa3":7000,"pep5":61000,"xander3":7600,"eric1":800,"misko1":800,"marianovella1":800,"marianovella2":2500,"eric2":2400,"misko2":2500,"misko3":10000,"marianovella3":10000,"eric3":9250,"henley3":20700,"seth4":21330,"dabria4":22950,"clarice4":81000,"dawn4":67500,"petula3":7200,"holly4":45900,"carl4":40500,"odile4":59400,"bebe4":81000,"otto4":877500,"dante4":864000,"vampirecameron4":1620000,"holly5":137700,"satine_easter5":1620000,"malcolm5":607500,"patty_the_valentines_cow5":4050000,"vampirecameron2":180000,"patty_the_valentines_cow3":450000,"gordon5":307800,"chloe3":58500,"floyd_the_fries5":323919,"emma5":210600,"lindsay4":40500,"otto3":292500,"maya5":162000,"regina4":108000,"beula4":67500,"caroleena_easter3":405000,"sunny4":121500,"satine_easter4":540000,"henry5":202500,"archie5":526500,"tyree5":64800,"rudolph3":22500,"jonas5":405000,"cannon5":1581525,"clarice3":27000,"benny5":1182600,"brock5":283500,"kevin2":27000,"xander4":21600,"keina4":135000,"kevin5":729000,"dabria5":68850,"charlie5":97200,"dustin3":240750,"cici3":18000,"caroleena_easter4":1215000,"cailey3":18000,"vampirecameron3":540000,"kiki4":129600,"molinda3":360000,"rocky5":486000,"stacy5":68850,"patrona5":48600,"daxxon3":27000,"molinda2":120000,"patty4":175500,"maggie5":64800,"rosie3":49500,"henry4":67500,"ashley5":162000,"michaela4":135000,"stix3":270000,"gordon4":102600,"dante3":288000,"petula5":64800,"chloe5":526500,"kondo5":729000,"cookie4":21600,"brock4":94500,"bumble3":27000,"danny4":108000,"tyree4":21600,"kondo4":243000,"sabrina4":94500,"zuzana3":63000,"melani3":13500,"dustin4":722250,"tristan4":54000,"clarice5":243000,"kevin4":243000,"gary5":364500,"avery5":567000,"penny5":575100,"regina5":324000,"leonard5":429219,"patty_the_valentines_cow4":1350000,"hermey3":29700,"maya4":54000,"wanda4":54000,"dallas_easter5":243000,"tatiana4":135000,"poplina4":23193,"michaela5":405000,"holly3":15300,"kiki5":388800,"xiomara5":323919,"ronnie5":704700,"mykii5":48600,"zuzana5":567000,"suneetha4":27000,"gracelynn4":40500,"shantira4":24300,"shantira5":72900,"gary4":121500,"poplina5":69579,"chloe4":175500,"xiomara4":107973,"dante5":2592000,"hermey5":267300,"scarlet4":27000,"sheldon4":148500,"molinda4":1080000,"sawyer3":22500,"patty5":526500,"kendla5":68850,"maggie4":21600,"harrison3":18900,"bernardo5":113400,"samir2":19200,"sawyer5":202500,"jonas4":135000,"maya3":18000,"tatiana5":405000,"lindsay5":121500,"bernardo4":37800,"cici5":162000,"cienna3":24300,"petula4":21600,"melani5":121500,"toni4":27000,"gigi4":94500,"henley5":186300,"bumble5":243000,"glady5":64800,"maui4":121500,"glady4":21600,"daxxon5":243000,"samir5":518400,"vampirecameron5":4860000,"penny4":191700,"sharie4":81000,"wendy4":256500,"sheldon5":445500,"stix5":2430000,"shun5":64800,"maritza5":972000,"fresa4":21600,"zuzana4":189000,"seth5":63990,"wendy5":769500,"yollie5":81000,"sawyer4":67500,"rudolph5":202500,"maui5":364500,"tracey5":202500,"cienna5":218700,"dawn5":202500,"bumble4":81000,"shun4":21600,"molinda5":3240000,"cailey5":162000,"sabrina5":283500,"prince4":202500,"tristan5":162000,"safiyah3":18000,"caroleena_easter5":3645000,"cici4":54000,"rosie5":445500,"trinity5":170100,"beula5":202500,"cookie5":64800,"mo5":67230,"keina5":405000,"tracey4":67500,"sid5":324000,"lesedi4":32400,"cannon3":175725,"otto5":2632500,"michaela3":45000,"avery4":189000,"prince5":607500,"misko5":64800,"eric4":21600,"marianovella5":64800,"misko4":21600,"prince3":67500,"marianovella4":21600,"sid4":108000,"rudolph4":67500,"trinity4":56700,"hermey4":89100,"carl5":121500,"cannon4":527175,"eric5":64800,"henley4":62100,"chuey5":64800,"maritza4":324000,"floyd_the_fries4":107973,"dustin5":2166750,"aimee_easter2":960000,"aimee_easter3":2880000,"aimee_easter4":8640000,"aimee_easter5":25920000,"danny5":324000,"leonard4":143073,"sharie5":243000,"cienna4":72900,"emma4":70200,"cailey4":54000,"ashley4":54000,"safiyah4":54000,"safiyah5":162000,"melani4":40500,"harrison4":56700,"harrison5":170100,"samir4":172800,"rocky4":162000,"rosie4":148500,"daxxon4":81000,"stix4":810000}