{"ursula3":7000,"maritza1":8000,"carmelita1":5500,"toni1":2700,"brock3":12000,"sabrina3":11000,"prince1":18000,"karina_costume2":2500,"andres1":800,"sid1":4950,"misty3":10000,"emily_halloween1":10000,"bimbi4":250000,"lola1":250,"malcolm_halloween1":3500,"pumpkin_cam3":91500,"bimbi1":10000,"bimbi2":34000,"poplina2":7000,"ceba3":5500,"scarlet3":19000,"triston1":1900,"hans1":230,"wendy3":15000,"shaun1":900,"bimbi3":100000,"malcolm_sdcc1":10000,"keina2":7400,"zozo1":3500,"cannon1":60000,"avery1":7000,"mo1":2000,"kiki3":11000,"kiki2":6500,"ursula1":800,"fresa2":4000,"maggie2":3800,"caedia2":4500,"maritza3":19800,"glady1":1000,"dante2":180000,"sid3":31000,"kiki1":3000,"henry1":2500,"trinity2":6000,"esmeralda_costume1":850,"carl1":3000,"misko1":1300,"fifi2":700,"sid2":13000,"bubba1":2500,"benny2":11000,"ronnie3":15000,"benny1":5000,"seth1":1200,"jonas1":1700,"chauncy1":850,"scarlet1":3500,"zuzana1":7500,"drew1":1000,"bernise1":570,"penny1":3000,"mykii2":1100,"ricky1":1400,"zobey1":1000,"melani1":2000,"cameron2":800,"bernise2":1100,"marianovella1":1300,"stacy1":1300,"mateo1":800,"andres2":2500,"dawn1":4000,"charlie3":12000,"pumpkin_cam1":10000,"ceba1":900,"winston1":230,"lola2":700,"mykii1":550,"cameron1":250,"patrona1":560,"wendy2":8000,"malcolm_halloween2":9500,"patty_sdcc1":11000,"fresa1":1500,"odile1":2800,"archie3":17000,"benny3":19000,"malcolm3":14000,"molinda1":60500,"fifi1":230,"leon1":3100,"rudolph1":5000,"zozo2":8000,"cici1":1800,"beula1":2500,"bernise3":3500,"gary3":15000,"caedia3":9200,"tyree1":1500,"bubba3":13999,"daxxon1":3000,"mario1":827,"nathan1":800,"jonas2":4500,"karina_costume1":950,"todd2":3000,"samir3":15000,"wanda2":9000,"hans3":1700,"gordon3":16000,"charlie1":2000,"nathan2":2500,"poplina1":3000,"derek1":900,"archie1":4000,"kevin1":3200,"francis1":850,"tally1":850,"rocky_costume1":900,"vas1":2500,"george1":800,"ceba2":1500,"bebe1":2500,"wendy5":100000,"hans2":700,"todd1":900,"chanel1":3800,"maribel1":5350,"derek3":7850,"suneetha2":6000,"satine_easter1":41500,"tatiana3":13000,"wendy1":4000,"malcolm5":105000,"avery3":17258,"dustin1":5500,"zozo3":15000,"seth3":13750,"sharie3":7800,"penny3":11700,"safiyah1":2500,"winston2":700,"charlie2":5000,"tatiana2":6000,"cameron3":2000,"ursula2":2400,"clarice1":6000,"maribel3":34500,"zuzana3":49000,"sunny1":4000,"lola5":13000,"regina1":2200,"mark1":800,"eric2":4000,"emily_halloween3":87500,"dallas_easter3":75000,"caedia1":2000,"harrison1":2500,"tristan1":1300,"misty1":890,"rosie1":4000,"chuey1":1800,"mateo3":7500,"ceba4":14000,"tracey2":5000,"fifi3":1700,"malcolm1":3700,"shantira1":1900,"kendla1":4000,"xander1":1900,"dante1":80000,"sabrina1":2700,"bumble2":17000,"sheldon3":15000,"kendla2":9000,"bernise4":8750,"kai3":11000,"keina1":5000,"petula1":1000,"pep2":5500,"samir1":3500,"ronnie1":3317,"maya1":2500,"connor2":5000,"suneetha1":2500,"ricky2":4000,"michaela2":29000,"eric1":1500,"rosie3":23000,"misko2":3500,"zozo5":110000,"humphrey1":900,"danny3":22999,"danny2":8500,"malcolm_halloween3":23000,"mo2":6900,"floyd_the_fries1":3450,"gary1":4000,"kai1":1300,"cienna1":2500,"wanda1":3100,"patrona3":3500,"zobey3":11000,"cameron4":5000,"sheldon1":3800,"humphrey2":2400,"maya2":6000,"stix1":70500,"drew2":3000,"emily_halloween2":28000,"andres3":7500,"maui1":4800,"winston4":4450,"bernardo1":2000,"winston3":1500,"cookie1":1300,"lola3":1900,"drew4":29750,"golden_hans3":15000,"bernise5":30500,"ricky4":25000,"lindsay1":3000,"hermey1":7500,"rocky_costume3":10000,"holly1":2000,"trinity1":2500,"sharie1":2500,"michaela1":9500,"astin1":3500,"omar1":1700,"cookie2":4500,"pumpkin_cam2":30000,"malcolm2":7500,"lesedi1":2000,"connor1":2500,"gary5":110000,"patty2":7800,"cici2":5000,"zobey2":3000,"emily_sdcc1":11000,"patty_the_valentines_cow1":80000,"kai2":3500,"sunny2":14000,"cameron5":12000,"emily_halloween5":540000,"humphrey3":10000,"maggie1":1500,"hammie3":13500,"george2":3000,"scarlet2":7500,"brock1":3000,"drew3":10000,"shun2":7000,"jonas3":13775,"xiomara2":7000,"bubba4":30000,"emma1":3000,"harrison2":6000,"clarice2":18000,"regina3":10000,"cannon2":120000,"kondo1":20000,"shun1":2000,"bumble1":7000,"mateo2":2800,"keina3":18000,"vas2":5000,"dabria1":1500,"patty1":4000,"lesedi3":12000,"maui3":17000,"jonas5":99000,"rocky_costume2":2700,"kondo3":115000,"gigi1":4000,"leonard2":7700,"esmeralda_costume2":2500,"chloe1":17325,"tally2":2500,"stacy2":4000,"patrona2":1300,"dustin2":16000,"xiomara3":14000,"xiomara5":86500,"tally3":9750,"leon3":15000,"pep1":1900,"vas3":9700,"tracey1":2600,"dallas_easter1":9500,"xiomara1":3500,"tatiana1":2500,"glady2":3000,"rocky1":3000,"jonas4":25000,"dustin3":35000,"tracey3":9000,"george3":9300,"francis2":2600,"shaun3":7500,"lola4":4100,"ronnie4":33500,"hammie5":72500,"chanel2":8700,"misty2":2900,"omar2":5500,"ashley1":3000,"gary4":55000,"ceba5":32000,"shaun2":2600,"patty3":16000,"tyree2":4500,"melani2":5100,"sunny3":25000,"patrona5":35000,"samir2":11000,"kendla3":25000,"gordon1":3500,"benny4":46000,"bubba2":5000,"cailey1":3000,"mario2":2500,"chauncy3":7100,"esmeralda_costume3":6000,"dallas_easter2":20000,"floyd_the_fries3":12000,"astin3":15250,"poplina3":18000,"mark2":2400,"bernardo2":5800,"archie2":8500,"omar3":13500,"chuey2":6000,"patrona4":9350,"karina_costume3":9400,"rudolph2":17000,"cailey2":7425,"emma2":5900,"carmelita3":19000,"yollie1":2800,"astin2":6900,"chauncy2":2400,"malcolm_halloween5":210000,"kevin3":10000,"rocky3":13000,"gracelynn3":16300,"leonard3":14100,"danny1":3200,"ricky3":10000,"chanel3":25000,"leon2":7000,"carmelita2":11000,"leonard4":50000,"rosie2":10000,"brock2":9000,"ronnie2":7400,"cameron_sdcc1":9950,"mario3":9000,"sawyer1":3000,"wendy4":35000,"maribel2":10000,"lesedi2":5000,"scarlet5":190000,"derek2":2600,"carl2":6000,"gracelynn1":1600,"gary2":8150,"caroleena_easter1":82000,"shantira2":4400,"carmelita4":40250,"bebe2":5600,"patty5":110000,"bubba5":150000,"fifi4":4750,"leonard1":3400,"triston3":10000,"hammie4":28500,"dabria2":5000,"trinity3":16999,"francis3":8600,"dabria3":13000,"bimbi5":650000,"bebe3":13000,"golden_hans5":72000,"astin5":81500,"ursula4":22000,"malcolm_sdcc2":26000,"penny2":9200,"vas5":75000,"lindsay2":8000,"vampirecameron1":115000,"malcolm_halloween4":62000,"maya3":18000,"stacy3":11000,"otto1":75000,"floyd_the_fries2":6200,"benny5":110000,"connor3":13750,"mykii3":3300,"henley2":6000,"henley1":2300,"daxxon2":7000,"dustin5":215000,"rosie5":185000,"mykii4":12000,"emily_sdcc3":90000,"todd3":9000,"avery2":12000,"misko3":13999,"sabrina2":7900,"seth2":3500,"caroleena_easter2":190000,"odile2":6600,"tristan2":3200,"dawn2":7000,"maggie3":16250,"yollie2":8000,"beula2":7500,"kevin2":5000,"maribel5":330000,"hans5":14500,"lindsay3":24000,"nathan3":8400,"cookie3":12000,"carl3":17000,"fifi5":10700,"toni2":7500,"safiyah2":5900,"hans4":4000,"malcolm_sdcc3":85000,"sawyer2":5500,"astin4":37050,"henry2":6000,"avery5":190000,"otto2":175000,"kondo2":46000,"fresa3":12000,"pep3":11500,"emily_sdcc2":30000,"golden_hans4":34000,"suneetha5":177500,"leon5":81000,"gracelynn2":5000,"maritza5":180000,"scarlet4":80000,"connor4":30000,"kendla4":85000,"triston2":5650,"hermey2":30000,"yollie3":23000,"gigi2":10500,"petula2":3300,"aimee_easter1":653000,"suneetha3":18500,"marianovella2":4000,"rocky2":6750,"carmelita5":150000,"sunny5":190000,"gordon2":7500,"shaun5":80000,"emily_halloween4":200000,"xiomara4":40000,"xander2":5700,"maggie5":90000,"zozo4":50000,"marianovella3":12000,"maui2":8900,"omar5":130000,"regina2":6600,"eric3":10000,"caedia5":130000,"tristan3":10000,"glady3":10000,"satine_easter2":100000,"bernardo3":15000,"tyree3":10000,"vas4":20000,"melani3":18500,"ronnie5":200000,"connor5":95000,"leon4":40000,"pumpkin_cam4":200000,"ashley2":8000,"mykii5":36000,"mo3":20000,"winston5":11000,"misty5":75000,"zuzana2":13000,"pumpkin_cam5":700000,"bebe5":177500,"mark3":7200,"patty_sdcc2":29000,"maui5":320000,"patty_the_valentines_cow2":212500,"dawn3":30000,"priscilla1":810,"lucia1":810,"kayce1":810,"lucia2":2700,"kayce2":2500,"kayce3":7300,"priscilla2":2000,"lucia3":9750,"priscilla3":7400,"lucia5":78000,"keina5":200000,"kayce5":75000,"lucia4":21000,"kayce4":22000,"penny5":180000,"amelie1":900,"pedma1":850,"tomos1":850,"tomos2":3500,"pedma2":4500,"amelie2":4850,"amelie3":12000,"tomos3":10000,"pedma3":11000,"amelie4":35000,"pedma4":27000,"amelie5":89000,"pedma5":81250,"wanda3":27900,"eric5":121500,"danny5":259200,"otto4":2025000,"toni4":72900,"stix2":211500,"kondo4":540000,"michaela3":85500,"mario5":66987,"rosie4":108000,"tally5":68850,"eric4":40500,"misty4":24030,"george5":64800,"clarice3":54000,"triston5":153900,"chauncy5":68850,"kendla5":324000,"kevin4":86400,"rocky_costume4":24300,"molinda2":181500,"patty4":108000,"pep5":153900,"penny4":81000,"shun3":18000,"andres5":64800,"safiyah3":22500,"cailey3":27000,"patty_the_valentines_cow3":720000,"prince2":54000,"suneetha4":67500,"todd4":24300,"archie4":108000,"dante3":720000,"chloe2":51975,"ricky5":113400,"rocky_costume5":72900,"cici3":16200,"sid4":133650,"sheldon5":307800,"sharie4":67500,"dustin4":148500,"melani4":54000,"maritza4":216000,"clarice5":486000,"sid5":400950,"henry3":22500,"toni3":24300,"rocky4":81000,"beula5":202500,"vampirecameron2":345000,"odile3":25200,"cailey4":81000,"chanel5":307800,"chuey3":16200,"malcolm_sdcc4":270000,"poplina5":243000,"dabria5":121500,"malcolm4":99900,"andres4":21600,"yollie5":226800,"emma4":81000,"rocky5":243000,"prince3":162000,"shun4":54000,"maui4":129600,"leonard5":275400,"gordon5":283500,"bumble3":63000,"carl5":243000,"floyd_the_fries5":279450,"trinity4":67500,"shaun4":24300,"marianovella4":35100,"emily_sdcc5":891000,"kai4":35100,"samir5":283500,"chauncy4":22950,"daxxon4":81000,"maya4":67500,"regina4":59400,"caroleena_easter5":6642000,"aimee_easter4":17631000,"zuzana4":202500,"zobey5":81000,"sheldon2":11400,"gigi5":324000,"tatiana4":67500,"zobey4":27000,"sheldon4":102600,"safiyah5":202500,"fresa5":121500,"nathan5":64800,"bebe4":67500,"ashley3":27000,"misko4":35100,"chanel4":102600,"emily_sdcc4":297000,"karina_costume4":25650,"esmeralda_costume4":22950,"emma3":27000,"george4":21600,"tracey5":210600,"brock5":243000,"cameron_sdcc3":89550,"charlie5":162000,"cannon3":540000,"charlie4":54000,"michaela5":769500,"gracelynn4":43200,"satine_easter4":1120500,"melani5":162000,"patty_sdcc5":891000,"samir4":94500,"shantira4":51300,"beula3":22500,"molinda3":544500,"holly5":162000,"aimee_easter2":1959000,"gordon4":94500,"sawyer3":27000,"wanda5":251100,"pep4":51300,"kiki4":81000,"sawyer4":81000,"bernardo4":54000,"sharie5":202500,"sawyer5":243000,"triston4":51300,"cameron_sdcc2":29850,"lesedi5":162000,"sharie2":7500,"sunny4":108000,"tally4":22950,"holly2":6000,"floyd_the_fries4":93150,"gigi3":36000,"archie5":324000,"lindsay4":81000,"maggie4":40500,"kiki5":243000,"stix3":634500,"poplina4":81000,"yollie4":75600,"caedia4":54000,"stacy5":105300,"bumble5":567000,"holly4":54000,"odile4":75600,"mario4":22329,"stix4":1903500,"odile5":226800,"satine_easter3":373500,"misko5":105300,"keina4":135000,"hermey3":67500,"regina5":178200,"maya5":202500,"shantira3":17100,"lindsay5":243000,"xander5":153900,"dawn5":324000,"dallas_easter5":769500,"kai5":105300,"cienna2":7500,"tyree5":121500,"dallas_easter4":256500,"xander3":17100,"emma5":243000,"cici4":48600,"mark5":64800,"patty_sdcc4":297000,"molinda4":1633500,"vampirecameron3":1035000,"daxxon3":27000,"prince4":486000,"caroleena_easter3":738000,"cailey5":243000,"satine_easter5":3361500,"wanda4":83700,"patty_sdcc3":99000,"mateo5":64800,"francis5":68850,"drew5":81000,"priscilla5":65610,"humphrey4":24300,"tyree4":40500,"henley3":20700,"mark4":21600,"holly3":18000,"todd5":72900,"priscilla4":21870,"maribel4":144450,"brock4":81000,"avery4":189000,"bumble4":189000,"clarice4":162000,"rudolph4":135000,"marianovella5":105300,"cookie4":35100,"harrison3":22500,"petula3":9000,"rudolph3":45000,"toni5":218700,"seth5":97200,"tatiana5":202500,"petula4":27000,"seth4":32400,"henry5":202500,"petula5":81000,"cienna3":22500,"karina_costume5":76950,"esmeralda_costume5":68850,"maritza2":24000,"omar4":45900,"nathan4":21600,"kondo5":1620000,"daxxon5":243000,"francis4":22950,"gracelynn5":129600,"harrison5":202500,"rudolph5":405000,"sabrina5":218700,"glady4":27000,"cameron_sdcc5":805950,"chloe3":155925,"harrison4":67500,"zuzana5":607500,"hermey5":607500,"beula4":67500,"dante5":6480000,"derek4":24300,"aimee_easter3":5877000,"cienna4":67500,"sabrina4":72900,"stix5":5710500,"cookie5":105300,"derek5":72900,"patty_the_valentines_cow5":6480000,"mo5":162000,"gigi4":108000,"shantira5":153900,"mateo4":21600,"chloe4":467775,"bernardo5":162000,"tristan5":105300,"cannon5":4860000,"trinity5":202500,"tomos5":68850,"dawn4":108000,"chuey5":145800,"tomos4":22950,"stacy4":35100,"otto3":675000,"aimee_easter5":52893000,"caroleena_easter4":2214000,"molinda5":4900500,"danny4":86400,"tracey4":70200,"chloe5":1403325,"cienna5":202500,"michaela4":256500,"henley4":62100,"henley5":186300,"ashley4":81000,"ashley5":243000,"safiyah4":67500,"cici5":145800,"henry4":67500,"kevin5":259200,"prince5":1458000,"patty_the_valentines_cow4":2160000,"cannon4":1620000,"vampirecameron4":3105000,"vampirecameron5":9315000,"dante4":2160000,"otto5":6075000,"hermey4":202500}