{"astin2":6000,"cameron1":250,"maggie1":800,"stacy1":840,"shun1":800,"shantira1":900,"mo1":830,"stacy3":8775,"rudolph1":2500,"carl3":9500,"clarice1":3000,"hermey1":3300,"leon1":2000,"suneetha1":990,"tyree1":800,"kevin1":9000,"toni1":900,"vas1":1800,"bumble1":3000,"maritza1":12000,"avery1":6000,"kondo1":11000,"cici1":2000,"fifi1":230,"patrona2":1300,"patty3":25000,"winston1":240,"astin1":2500,"bernise1":600,"kiki1":4800,"zuzana2":18000,"poplina1":850,"dabria1":850,"cookie1":800,"trinity1":2000,"mykii1":600,"sunny2":10000,"lola1":250,"scarlet1":950,"zuzana1":7000,"cameron2":800,"mykii2":1300,"winston2":700,"fifi2":700,"lola4":4500,"hans2":700,"lola2":700,"zozo2":3000,"hans1":230,"fifi3":1700,"benny1":15000,"patrona1":600,"chloe1":5000,"bebe1":3000,"kondo2":28000,"emma1":2500,"regina1":4500,"lesedi1":1050,"petula1":750,"carmelita1":5000,"jonas1":4850,"malcolm1":6500,"rocky3":25000,"chuey1":800,"patty1":5000,"yollie1":980,"zozo1":1000,"charlie1":1000,"sharie1":2849,"lindsay1":1100,"carmelita2":12000,"wanda1":1800,"sunny1":4000,"chanel3":10549,"cienna1":2700,"gordon1":4000,"penny1":7100,"cannon1":18000,"maui1":4000,"stix1":30000,"henry1":2000,"archie1":6500,"gary2":12500,"daxxon1":3000,"kendla1":850,"safiyah1":2000,"xander1":800,"gary1":5000,"cameron3":2000,"cameron4":4700,"tristan1":2000,"keina1":5000,"carl2":3250,"maya1":2000,"sheldon1":5200,"brock1":3500,"tatiana1":4500,"tracey1":2500,"harrison1":2000,"dawn1":2500,"charlie2":3000,"rosie1":5000,"dustin1":30000,"leonard1":4900,"patrona4":10000,"dante1":32000,"floyd_the_fries1":3700,"holly1":1700,"cailey1":2000,"leonard3":20000,"tyree2":2100,"cookie2":2300,"vas3":8300,"cici2":5000,"chanel1":1300,"michaela1":4000,"astin5":63000,"bernardo1":1038,"poplina2":2500,"maggie2":2200,"tracey3":10000,"stacy2":2500,"bernise2":1300,"maribel1":5000,"molinda1":45000,"carmelita3":25000,"archie3":26000,"danny1":3500,"vas4":17000,"stix2":80000,"melani1":1500,"hans4":4000,"henry2":5000,"gigi1":3500,"lesedi3":12000,"henley1":2300,"sunny3":27000,"gracelynn1":1000,"chuey3":9000,"leon3":10000,"xander2":2000,"safiyah2":5500,"shantira2":2200,"hans3":1500,"ronnie3":28000,"hans5":15000,"xiomara3":23800,"benny3":38000,"wendy1":9500,"samir1":6000,"prince1":7000,"gary3":24000,"beula1":2500,"kiki3":21000,"carl1":1300,"suneetha2":3000,"vas2":3500,"zozo3":10000,"rudolph2":7500,"rocky2":13000,"holly2":4800,"clarice2":9000,"lola3":1800,"sabrina3":20000,"rocky1":6000,"odile1":2000,"ronnie1":8700,"sabrina1":3500,"patty_the_valentines_cow1":50000,"yollie2":2900,"maritza3":45000,"avery2":13000,"brock3":16500,"sheldon3":25000,"floyd_the_fries3":16000,"kevin3":35000,"shun2":2400,"bebe2":8000,"wendy3":27000,"malcolm3":25000,"tatiana3":20000,"penny3":26000,"kendla2":2500,"shun3":5900,"leon2":4800,"malcolm2":12000,"patty2":15000,"scarlet2":3000,"mo2":2500,"kendla3":8000,"chanel2":3500,"xiomara2":10000,"brock2":8500,"toni2":2800,"mykii3":3600,"poplina3":8000,"maribel3":55000,"beula2":7500,"hermey2":8250,"bernise5":42000,"jonas3":37999,"ashley1":2000,"xiomara4":66000,"petula2":2300,"fifi5":11500,"sawyer1":2500,"kondo3":60000,"kendla4":20000,"poplina4":22000,"tristan2":4500,"daxxon2":7700,"cookie3":5000,"sid1":3000,"maui3":20000,"maribel2":17500,"benny4":89000,"dallas_easter1":2500,"dallas_easter3":22500,"cookie4":25000,"xiomara1":3999,"dallas_easter2":7500,"lesedi2":3275,"winston3":1500,"winston4":4000,"cameron5":13000,"lola5":10000,"fifi4":4300,"wanda2":4900,"patty4":74000,"regina3":21000,"satine_easter1":22000,"chuey2":2100,"chloe3":38500,"chloe2":14000,"gracelynn2":3500,"lindsay2":3000,"vampirecameron1":65000,"avery3":27000,"melani2":4500,"astin3":13000,"tyree3":6000,"scarlet5":72500,"gigi5":200000,"patty_the_valentines_cow2":115000,"caroleena_easter1":55000,"floyd_the_fries2":7875,"bernardo3":11000,"aimee_easter1":350000,"tracey2":6750,"rosie2":10000,"bernise3":4000,"dallas_easter5":210000,"dawn2":7000,"samir3":25000,"zozo4":25000,"charlie3":10000,"harrison2":4500,"henry3":12750,"ronnie2":16000,"zozo5":65000,"yollie3":9000,"sharie3":10000,"cailey2":6100,"otto1":35000,"dabria2":2400,"scarlet3":10000,"sabrina2":10750,"suneetha3":9000,"toni3":11000,"sawyer3":24000,"michaela2":16000,"benny2":25000,"yollie4":27000,"molinda2":101000,"carmelita4":70000,"maui2":10000,"winston5":13000,"patrona3":3500,"odile2":5500,"tatiana2":10000,"gigi2":11000,"otto4":509000,"maggie4":21000,"leon5":66500,"satine_easter2":70000,"scarlet4":23500,"danny3":17500,"suneetha4":25600,"sheldon2":13000,"trinity2":5000,"bebe3":17050,"cienna2":7500,"emma2":6000,"sawyer2":7500,"poplina5":70000,"caroleena_easter2":110000,"wendy2":17450,"stacy5":76500,"satine_easter3":200000,"astin4":30000,"gordon3":24250,"dallas_easter4":60000,"bernardo2":3000,"henley2":7500,"chanel5":90000,"maya2":4950,"carmelita5":250000,"prince2":20000,"leonard2":11000,"archie5":258500,"archie2":15000,"ronnie4":80000,"dante3":220000,"otto2":99200,"archie4":74999,"rosie3":30000,"tristan3":13000,"keina3":22595,"sid3":21000,"keina2":10000,"trinity3":13600,"dustin2":75000,"leon4":25000,"dante2":85000,"sharie2":5000,"chanel4":25000,"ashley2":5000,"bumble2":9000,"charlie5":85000,"emma3":15000,"gordon2":10000,"caroleena_easter3":295000,"suneetha5":81000,"ashley3":14000,"wanda3":9500,"maggie3":9650,"sid2":7700,"jonas2":13000,"mo3":6500,"xander3":7550,"odile3":18000,"vampirecameron2":190000,"samir2":12000,"stacy4":21000,"mykii4":10000,"gigi3":26000,"kevin2":23000,"danny2":9600,"beula3":20000,"keina4":90000,"regina2":12000,"malcolm4":75000,"caroleena_easter4":875000,"penny2":16000,"lindsay3":15000,"toni4":25000,"bernise4":10000,"kiki2":10999,"dawn3":20000,"vas5":45000,"maritza2":25571,"bebe5":250000,"maya5":163000,"sunny5":220000,"cannon2":50000,"satine_easter4":590000,"maribel5":600000,"shantira3":8100,"petula3":9000,"gordon4":53000,"gracelynn3":15500,"kevin5":500000,"lindsay4":37000,"charlie4":28000,"omar1":800,"triston2":2500,"triston1":850,"seth1":790,"omar2":2400,"omar3":10000,"seth3":7000,"triston3":10000,"seth2":2300,"omar4":22000,"omar5":75000,"triston5":72000,"triston4":21000,"gracelynn5":100000,"dabria3":7500,"pep1":800,"glady1":800,"pep2":2500,"fresa1":800,"glady2":2350,"fresa2":2000,"pep3":8000,"glady3":9500,"fresa3":7200,"rosie4":135000,"xander5":64800,"petula4":20250,"molinda4":1215000,"gary4":135000,"molinda5":3645000,"clarice3":27000,"holly4":45900,"patty_the_valentines_cow3":450000,"kendla5":68850,"hermey4":89100,"clarice4":81000,"bumble5":243000,"tristan4":54000,"patrona5":48600,"wanda4":48600,"sheldon5":421200,"cienna4":72900,"dabria5":68850,"kondo5":891000,"carl5":105300,"jonas4":130950,"kondo4":297000,"sheldon4":140400,"brock5":283500,"maya3":18000,"gary5":405000,"avery4":162000,"shun5":64800,"avery5":486000,"lindsay5":89100,"bernardo4":28026,"benny5":1215000,"brock4":94500,"zuzana3":63000,"henley3":20700,"holly3":15300,"melani3":13500,"otto3":315000,"zuzana5":567000,"hermey3":29700,"tyree4":21600,"safiyah3":18000,"jonas5":392850,"kiki4":129600,"maui4":108000,"tatiana4":121500,"yollie5":79380,"chloe4":135000,"penny4":191700,"vampirecameron3":585000,"daxxon3":27000,"tyree5":64800,"danny5":283500,"mo4":22410,"prince4":189000,"trinity5":162000,"prince3":63000,"sid4":81000,"satine_easter5":1782000,"mo5":67230,"sabrina4":94500,"rocky4":162000,"aimee_easter5":28350000,"shun4":21600,"tatiana5":364500,"dustin3":270000,"wendy5":769500,"cookie5":64800,"floyd_the_fries4":99900,"gordon5":324000,"maritza4":324000,"petula5":60750,"rosie5":405000,"tristan5":162000,"ashley5":162000,"cailey3":18000,"cannon3":162000,"cienna3":24300,"beula5":202500,"michaela5":324000,"cailey5":162000,"malcolm5":526500,"penny5":575100,"caroleena_easter5":4455000,"michaela3":36000,"dante4":864000,"aimee_easter4":9450000,"maggie5":64800,"shantira4":24300,"wendy4":256500,"safiyah4":54000,"danny4":94500,"maribel4":135000,"toni5":72900,"clarice5":243000,"sharie4":76923,"kiki5":388800,"melani4":40500,"dabria4":22950,"sid5":243000,"melani5":121500,"sharie5":230769,"ashley4":54000,"dawn4":67500,"rudolph5":202500,"rocky5":486000,"leonard5":396900,"floyd_the_fries5":299700,"rudolph3":22500,"cici5":162000,"keina5":405000,"trinity4":54000,"vampirecameron5":5265000,"zuzana4":189000,"tracey5":202500,"seth5":63990,"bumble3":27000,"wanda5":145800,"maritza5":972000,"samir5":486000,"regina4":121500,"lesedi5":85050,"emma4":67500,"emma5":202500,"bernardo5":84078,"carl4":35100,"bebe4":81000,"leonard4":132300,"molinda3":405000,"holly5":137700,"ronnie5":704700,"chloe5":405000,"henley5":186300,"dante5":2592000,"gracelynn4":27000,"gigi4":94500,"sawyer4":67500,"sawyer5":202500,"stix3":270000,"cienna5":218700,"sunny4":108000,"patty5":405000,"seth4":21330,"shantira5":72900,"regina5":364500,"patty_the_valentines_cow5":4050000,"odile4":54000,"vampirecameron4":1755000,"beula4":67500,"henry5":162000,"cannon5":1458000,"xander4":21600,"cici3":18000,"odile5":162000,"henry4":54000,"michaela4":108000,"dustin4":810000,"kevin4":243000,"patty_the_valentines_cow4":1350000,"maya4":54000,"xiomara5":323919,"mykii5":48600,"hermey5":267300,"harrison3":18000,"glady5":64800,"pep4":21600,"glady4":21600,"daxxon5":243000,"stix5":2430000,"fresa4":21600,"maui5":324000,"dawn5":202500,"bumble4":81000,"pep5":64800,"sabrina5":283500,"cici4":54000,"aimee_easter2":1050000,"aimee_easter3":3150000,"tracey4":67500,"henley4":62100,"cailey4":54000,"safiyah5":162000,"harrison4":54000,"harrison5":162000,"samir4":162000,"dustin5":2430000,"prince5":567000,"daxxon4":81000,"cannon4":486000,"otto5":2835000,"stix4":810000,"rudolph4":67500}